telegraph_sdk/__init__.py
telegraph_sdk/api_async.py
telegraph_sdk-0.1.4.dist-info/METADATA
telegraph_sdk-0.1.4.dist-info/WHEEL
telegraph_sdk-0.1.4.dist-info/top_level.txt
telegraph_sdk-0.1.4.dist-info/RECORD
